streamingds/__init__.py
streamingds/bloomfilter.py
streamingds/countminsketch.py
streamingds/countminsketch.so
streamingds/hashing.py
streamingds/heap.py
streamingds/hyperloglog.py
streamingds/redis/__init__.py
streamingds/redis/base.py
streamingds/redis/bloomfilter.py
streamingds/redis/countminsketch.py
streamingds/redis/hashing.py
streamingds-0.2.0.dist-info/DESCRIPTION.rst
streamingds-0.2.0.dist-info/METADATA
streamingds-0.2.0.dist-info/metadata.json
streamingds-0.2.0.dist-info/RECORD
streamingds-0.2.0.dist-info/top_level.txt
streamingds-0.2.0.dist-info/WHEEL
