Metadata-Version: 2.0
Name: streamingds
Version: 0.2.0
Summary: UNKNOWN
Home-page: UNKNOWN
Author: Daniel Truemper
Author-email: truemped@gmail.com
License: UNKNOWN
Platform: UNKNOWN
Requires-Dist: bitstring
Requires-Dist: pyhashxx
Requires-Dist: cytoolz
Provides-Extra: redis
Requires-Dist: redis; extra == 'redis'
Requires-Dist: hiredis; extra == 'redis'
Provides-Extra: test
Requires-Dist: pytest; extra == 'test'
Requires-Dist: pytest-cov; extra == 'test'
